llm_bedrock_nova.py
llm_bedrock_nova-0.1.1.dist-info/METADATA
llm_bedrock_nova-0.1.1.dist-info/WHEEL
llm_bedrock_nova-0.1.1.dist-info/entry_points.txt
llm_bedrock_nova-0.1.1.dist-info/licenses/LICENSE
llm_bedrock_nova-0.1.1.dist-info/RECORD
