Metadata-Version: 2.4
Name: llm-bedrock-nova
Version: 0.1.1
Summary: LLM plugin for Amazon's Nova on AWS Bedrock
Project-URL: Homepage, https://github.com/watany-dev/llm-bedrock-nova
Author: Sean Blakey, Will Sorenson
License: Apache-2.0
License-File: LICENSE
Classifier: License :: OSI Approved :: Apache Software License
Requires-Dist: boto3>=1.35.92
Requires-Dist: httpx>=0.28.1
Requires-Dist: pillow>=11.1.0
